{"f":[{"name":"ana","quantity":172},{"name":"micaela","quantity":234},{"name":"valentina","quantity":315},{"name":"romina","quantity":356},{"name":"sofia","quantity":376},{"name":"florencia","quantity":378},{"name":"agustina","quantity":380},{"name":"camila","quantity":453},{"name":"lucia","quantity":555},{"name":"maria","quantity":951}],"m":[{"name":"bruno","quantity":258},{"name":"rodrigo","quantity":273},{"name":"joaquin","quantity":289},{"name":"nicolas","quantity":302},{"name":"matias","quantity":343},{"name":"agustin","quantity":375},{"name":"lucas","quantity":441},{"name":"juan","quantity":470},{"name":"facundo","quantity":526},{"name":"santiago","quantity":561}]}